python_toolbox_przemek/__init__.py
python_toolbox_przemek/toolbox_venv.py
python_toolbox_przemek-0.4.3.dist-info/METADATA
python_toolbox_przemek-0.4.3.dist-info/WHEEL
python_toolbox_przemek-0.4.3.dist-info/entry_points.txt
python_toolbox_przemek-0.4.3.dist-info/top_level.txt
python_toolbox_przemek-0.4.3.dist-info/RECORD
