Metadata-Version: 2.4
Name: python-toolbox-przemek
Version: 0.4.3
Summary: We want to provide basic tools for our day-to-day work.
Author: przemek@sagalo.pro
Requires-Python: <4,>=3.11
Requires-Dist: poetry==2.2.0
Requires-Dist: pynvim==0.5.2
Requires-Dist: debugpy==1.8.14
Provides-Extra: lint
Requires-Dist: black==24.2.0; extra == "lint"
Requires-Dist: isort==5.13.2; extra == "lint"
Requires-Dist: nbqa==1.9.1; extra == "lint"
Requires-Dist: ruff==0.14.5; extra == "lint"
Provides-Extra: notebook
Requires-Dist: nbstripout==0.8.1; extra == "notebook"
Requires-Dist: jupytext==1.17.0; extra == "notebook"
Requires-Dist: ipykernel==6.29.5; extra == "notebook"
Provides-Extra: tests
Requires-Dist: coverage==7.8.2; extra == "tests"
Requires-Dist: pytest-xdist==3.8.0; extra == "tests"
Requires-Dist: pytest-datadir==1.8.0; extra == "tests"
